Arhitecture/verilog/arst/arst.sv
module async_rs_trigger(output reg q, q_inv, input wire r, s);
    always @(r or s) begin 
        case ({r,s})
            2'b01: begin
                q = 1'b1;
            end
            2'b10: begin
                q = 1'b0;
            end
            2'b11: begin
                q = 1'bx;
            end
        endcase
        q_inv = ~q;
    end
    
endmodule

Arhitecture/verilog/arst/arst_tb.sv
`include "arst.sv"

module arst_tb;
    reg r, s;
    wire q, nq;

    async_rs_trigger rst(q, nq, r, s);

    initial begin
        $dumpfile("dump.vcd");
        $dumpvars(1, arst_tb);
        $monitor("%0t: r=%b s=%b q=%b", $time, r, s, q);

            r = 0; s = 0;
        #1; r = 0; s = 1;
        #1; r = 1; s = 1;
        #1; r = 1; s = 0;
        #1; r = 0; s = 1;
        #1; r = 1; s = 1;
        #1; r = 0; s = 0;
        #1; r = 1; s = 0;
        #1; r = 0; s = 0;
        $finish;
    end  
endmodule

Arhitecture/verilog/arst/dump.vcd
$date
	Sat Oct 29 13:05:25 2022
$end
$version
	Icarus Verilog
$end
$timescale
	1s
$end
$scope module arst_tb $end
$var wire 1 ! q $end
$var wire 1 " nq $end
$var reg 1 # r $end
$var reg 1 $ s $end
$upscope $end
$enddefinitions $end
#0
$dumpvars
0$
0#
x"
x!
$end
#1
0"
1!
1$
#2
x"
x!
1#
#3
1"
0!
0$
#4
0"
1!
1$
0#
#5
x"
x!
1#
#6
0$
0#
#7
1"
0!
1#
#8
0#
