Arhitecture/verilog/counter/counterm.sv
module counterm #(parameter N = 4) (
    output reg[N-1:0] out,
    input clk,
    input reset,
    input enable
   	);

  always @ (posedge clk) begin
    if (enable) begin
      if (reset) 
        out = 0;       
      else 
      	out = out + 1; 
    end else begin
      out = out;
    end
  end
endmodule

Arhitecture/verilog/counter/counterm_tb.sv
`include "counterm.sv"

module counterm_tb #(parameter _N = 5);
    reg clk, reset, enable;
    wire[_N-1:0] out;
    
    counterm #(_N) _counterm(out, clk, reset, enable);   // mod 2**5 
    //wire[4-1:0] out4;
    //counterm _counterm(out4, clk, reset, enable); // mod 2**4 (default) 

    initial begin
        $dumpfile("dump.vcd");
        $dumpvars(1, counterm_tb);

      	clk = 0;
      	reset = 1;
        enable = 1;
        #1 reset = 0;
        #2 reset = 1;
        #2 reset = 0;      
      	#20 $finish;

    end

    always #1 clk = ~clk;
  
    always @(posedge clk) 
        $display("%0t\t%b %b %b %b == %d", $time, clk, reset, enable, out, out);
endmodule

Arhitecture/verilog/counter/dump.vcd
$date
	Sat Oct 29 13:46:42 2022
$end
$version
	Icarus Verilog
$end
$timescale
	1s
$end
$scope module counterm_tb $end
$var wire 5 ! out [4:0] $end
$var reg 1 " clk $end
$var reg 1 # enable $end
$var reg 1 $ reset $end
$upscope $end
$enddefinitions $end
#0
$dumpvars
1$
1#
0"
bx !
$end
#1
1"
0$
#2
0"
#3
b0 !
1"
1$
#4
0"
#5
b1 !
1"
0$
#6
0"
#7
b10 !
1"
#8
0"
#9
b11 !
1"
#10
0"
#11
b100 !
1"
#12
0"
#13
b101 !
1"
#14
0"
#15
b110 !
1"
#16
0"
#17
b111 !
1"
#18
0"
#19
b1000 !
1"
#20
0"
#21
b1001 !
1"
#22
0"
#23
b1010 !
1"
#24
0"
#25
b1011 !
1"
